ccxt_download/__init__.py
ccxt_download/constants.py
ccxt_download/public.py
ccxt_download/utilities.py
ccxt_download-0.4.1.dist-info/LICENSE
ccxt_download-0.4.1.dist-info/METADATA
ccxt_download-0.4.1.dist-info/WHEEL
ccxt_download-0.4.1.dist-info/top_level.txt
ccxt_download-0.4.1.dist-info/RECORD
