Metadata-Version: 2.1
Name: ccxt_download
Version: 0.4.1
Summary: A lightweight package to efficiently download cryptocurrency data using CCXT.
Author-email: Kieran Mackle <kemackle98@gmail.com>
Project-URL: Homepage, https://github.com/kieran-mackle/ccxt-download
Project-URL: Bug Tracker, https://github.com/kieran-mackle/ccxt-download/issues
Classifier: Programming Language :: Python :: 3
Classifier: License :: OSI Approved :: MIT License
Classifier: Operating System :: OS Independent
Requires-Python: >=3.11
License-File: LICENSE
Requires-Dist: ccxt >=4.0.112
Requires-Dist: pandas >=2.1.1
Requires-Dist: aiolimiter >=1.1.0
Provides-Extra: dev
Requires-Dist: black >=23.9.1 ; extra == 'dev'
Requires-Dist: commitizen >=3.10.0 ; extra == 'dev'
Requires-Dist: pre-commit >=3.4.0 ; extra == 'dev'
